{
  "collapse-filter": true,
  "search": "",
  "showTags": false,
  "showAttachments": false,
  "hideUnresolved": false,
  "showOrphans": true,
  "collapse-color-groups": false,
  "colorGroups": [
    {
      "query": "path:\"AI Generated\"",
      "color": {
        "a": 1,
        "rgb": 16749824
      }
    },
    {
      "query": "tag:#Agilité",
      "color": {
        "a": 1,
        "rgb": 65297
      }
    },
    {
      "query": "path:Skills  ",
      "color": {
        "a": 1,
        "rgb": 16487680
      }
    },
    {
      "query": "tag:#SoftwareCraft ",
      "color": {
        "a": 1,
        "rgb": 5766414
      }
    },
    {
      "query": "tag:#Tests  ",
      "color": {
        "a": 1,
        "rgb": 5766414
      }
    },
    {
      "query": "tag:#Korea  ",
      "color": {
        "a": 1,
        "rgb": 0
      }
    },
    {
      "query": "path:\"Notes Permanentes/Vie Perso\"  ",
      "color": {
        "a": 1,
        "rgb": 16777215
      }
    },
    {
      "query": "path:\"Notes Permanentes/Projets/Oli's Lab\"  ",
      "color": {
        "a": 1,
        "rgb": 15727012
      }
    },
    {
      "query": "path:\"Notes Permanentes/Projets/KicksFolio\"  ",
      "color": {
        "a": 1,
        "rgb": 16711680
      }
    },
    {
      "query": "path:\"Notes Permanentes/Contenu & Créatif\"  ",
      "color": {
        "a": 1,
        "rgb": 16418181
      }
    },
    {
      "query": "path:\"Notes Permanentes/Code\"  ",
      "color": {
        "a": 1,
        "rgb": 1266086
      }
    }
  ],
  "collapse-display": true,
  "showArrow": true,
  "textFadeMultiplier": 0,
  "nodeSizeMultiplier": 1.29193382411145,
  "lineSizeMultiplier": 1.08713686376949,
  "collapse-forces": true,
  "centerStrength": 0.727380669674662,
  "repelStrength": 20,
  "linkStrength": 1,
  "linkDistance": 30,
  "scale": 0.022133039044909097,
  "close": true
}